2_PROJECT(RISC_processor)/pipe_MIPS32.v
// Pilpeline description of a
// 32-bit RISC processor (MIPS32)
// Here a sub-set of Instructions are taken from
// MIPS32 instruction set and implemented using a
//pipeline in verilog.

module pipe_MIPS(
    clk1, clk2
);

input clk1, clk2; // A dual phase shifted clock design of pipeline is used

//IF (Instruction fetch) and ID latches.
reg [31:0] PC, IF_ID_IR, IF_ID_NPC;

//ID(Instruction Decode) and EX(Execution) latches(register).
reg [31:0] ID_EX_IR, ID_EX_NPC, ID_EX_A, ID_EX_B, ID_EX_Imm;

//Type of Instruction
//types: R-R, R-Imm, Load, Branch.
reg [2:0] ID_EX_type, EX_MEM_type, MEM_WB_type;

//EX and MEM(Memory access/Branch completion) latches.
reg [31:0] EX_MEM_IR, EX_MEM_ALUout, EX_MEM_B;
reg EX_MEM_Cond;    //Condition for branching

// MEM and WB(Register Write Back) latches.
reg [31:0]  MEM_WB_IR, MEM_WB_LMD, MEM_WB_ALUout;

reg [31:0] Reg [0:31];    //Register bank (32 x 32 bits)
reg [31:0] Mem [0:1023];  //1024 x 32 bits memory

// The op-code (6-bit) declaration
parameter ADD = 6'b000000,
          SUB = 6'b000001,
          AND = 6'b000010,
          OR  = 6'b000011,
          SLT = 6'b000100,
          MUL = 6'b000101,
          HLT = 6'b111111,
          LW  = 6'b001000,
          SW  = 6'b001001,
          ADDI= 6'b001010,
          SUBI= 6'b001011,
          SLTI= 6'b001100,
          BNEQZ = 6'b001101,
          BEQZ  = 6'b001110;

//Instruction type
parameter RR_ALU = 3'b000,
          RM_ALU = 3'b001,
          LOAD   = 3'b010,
          STORE  = 3'b011,
          BRANCH = 3'b100,
          HALT   = 3'b101;

reg HALTED; // Set after HLT instruction completes WB stage

reg BRANCH_TAKEN; //Required to disable instructions after branch

//Stages of the pipeline:
// IF stage

always @(posedge clk1)
begin
    if (HALTED == 0)
    begin
        if (((EX_MEM_IR[31:26] == BEQZ) && (EX_MEM_Cond == 1)) || 
             (EX_MEM_IR[31:26] == BNEQZ) && (EX_MEM_Cond == 0))
            begin
                IF_ID_IR     <= #2 Mem[EX_MEM_ALUout];
                BRANCH_TAKEN <= #2 1'b1;
                IF_ID_NPC    <= #2 EX_MEM_ALUout + 1;
                PC           <= #2 EX_MEM_ALUout + 1;
            end
        else
        begin
            IF_ID_IR  <= #2 Mem[PC];
            IF_ID_NPC <= #2 PC + 1;
            PC        <= #2 PC + 1;
        end
    end
end

// ID stage
always @(posedge clk2)
begin
    if (HALTED == 0)
        begin
            if (IF_ID_IR[25:21] == 5'b00000) ID_EX_A = 0;
            else
                ID_EX_A <= #2 Reg[IF_ID_IR[25:21]];  // rs

            if (IF_ID_IR[20:16] == 5'b00000) ID_EX_B <= 0;
            else
                ID_EX_B <= #2 Reg[IF_ID_IR[20:16]];  // rt

            ID_EX_NPC <= #2 IF_ID_NPC;
            ID_EX_IR  <= #2 IF_ID_IR;
            ID_EX_Imm <= #2 {{16{IF_ID_IR[15]}},{IF_ID_IR[15:0]}};

          case(IF_ID_IR[31:26])
            ADD,SUB,AND,OR,SLT,MUL : #2 ID_EX_type <= RR_ALU;
            ADDI,SUBI,SLTI         : #2 ID_EX_type <= RM_ALU;
            LW                     : #2 ID_EX_type <= LOAD;
            SW                     : #2 ID_EX_type <= STORE;
            BNEQZ,BEQZ             : #2 ID_EX_type <= BRANCH;
            HLT                    : #2 ID_EX_type <= HALT;
            default                : #2 ID_EX_type <= HALT;  //invalid opcode
          endcase
        end
end

// EX stage
always @(posedge clk1)
begin
   if (HALTED == 0)
    begin
        EX_MEM_type  <= #2 ID_EX_type;
        EX_MEM_IR    <= #2 ID_EX_IR;
        BRANCH_TAKEN <= 0;

        case (ID_EX_type)
            RR_ALU: begin
                      case (ID_EX_IR[31:26])
                        ADD  : EX_MEM_ALUout <= #2 ID_EX_A + ID_EX_B;
                        SUB  : EX_MEM_ALUout <= #2 ID_EX_A - ID_EX_B;
                        AND  : EX_MEM_ALUout <= #2 ID_EX_A & ID_EX_B;
                        OR   : EX_MEM_ALUout <= #2 ID_EX_A | ID_EX_B;
                        SLT  : EX_MEM_ALUout <= #2 ID_EX_A < ID_EX_B;
                        MUL  : EX_MEM_ALUout <= #2 ID_EX_A * ID_EX_B;
                          default: EX_MEM_ALUout <= #2 32'hxxxxxxxx;
                      endcase
                    end  
            RM_ALU: begin
                      case (ID_EX_IR[31:26])
                        ADDI  : EX_MEM_ALUout <= #2 ID_EX_A + ID_EX_Imm;
                        SUBI  : EX_MEM_ALUout <= #2 ID_EX_A - ID_EX_Imm;
                        SLTI  : EX_MEM_ALUout <= #2 ID_EX_A < ID_EX_Imm;
                        default: EX_MEM_ALUout <= #2 32'bxxxxxxxx;
                      endcase
                    end 
            LOAD,STORE: begin
                          EX_MEM_ALUout <= #2 ID_EX_A + ID_EX_Imm;
                          EX_MEM_B      <= #2 ID_EX_B;
                        end
            BRANCH: begin
                      EX_MEM_ALUout <= #2 ID_EX_NPC + ID_EX_Imm;
                      EX_MEM_Cond   <= #2 (ID_EX_A == 0);
                    end                
        endcase
    end
end

// MEM stage
always @(posedge clk2)
begin
    if(HALTED==0)
    begin
        MEM_WB_IR <= #2 EX_MEM_IR;
        MEM_WB_type <= #2 EX_MEM_type;

        case (MEM_WB_type)
          RR_ALU,RM_ALU  : #2 MEM_WB_ALUout <= EX_MEM_ALUout;

          LOAD           : #2 MEM_WB_LMD <= #2 Mem[EX_MEM_ALUout];

          STORE          : if (BRANCH_TAKEN == 0)
                               MEM_WB_LMD <= #2 EX_MEM_B;
        endcase
    end
end

//WB stage
always @(posedge clk1)
begin
    if(BRANCH_TAKEN == 0)
    begin
        case (MEM_WB_type)
          RR_ALU  : Reg[MEM_WB_IR[15:11]] <= #2 MEM_WB_ALUout; //rd
          RM_ALU  : Reg[MEM_WB_IR[20:16]] <= #2 MEM_WB_ALUout; //rt
          LOAD    : Reg[MEM_WB_IR[20:16]] <= #2 MEM_WB_LMD;    //rt
          HALT    : HALTED <= #2 1'b1;
        endcase
    end
end

endmodule

2_PROJECT(RISC_processor)/test2.v
// Test program to run on the
// 32-bit RISC processor
// Program :
// Load a word stored in memory location Mem[120]
// to a register
// Subtracting 10 from the stored value
// Store the result in memory location Mem[121]

`timescale 1ns/10ps
`include "pipe_MIPS32.v"

module test2;
reg clk1, clk2;
integer k;

//instantiate the processor

pipe_MIPS risc(clk1,clk2);

//Generation of Clock signals
initial
begin
    clk1 = 0;
    clk2 = 0;
    repeat(20)
    begin
        #5 clk1 = 1; #5 clk1 = 0;
        #5 clk2 = 1; #5 clk2 = 0;
    end
end

// Initializing the registers and storing
// program in the memory Mem[]
initial
  begin
      for(k=0;k<32;k++)
          risc.Reg[k] = k;

      //Loading the program in memory
      risc.Mem[1] = 32'h28010078;  // ADDI R1,R0,120
      risc.Mem[2] = 32'h0ce77800;  // OR R7,R7,R7  DUMMY INSTR
      risc.Mem[3] = 32'h20220000;  // LW R2,0(R1)
      risc.Mem[4] = 32'h0ce77800;  // OR R7,R7,R7  DUMMY INSTR
      risc.Mem[5] = 32'h2c42000a;  // SUBI R2,R2,10
      risc.Mem[6] = 32'h0ce77800;  // OR R7,R7,R7  DUMMY INSTR
      risc.Mem[7] = 32'h24220001;  // SW R2,1(R1)
      risc.Mem[8] = 32'hfc000000;  // HLT

      risc.Mem[120] = 40;
      risc.PC = 1;
      risc.HALTED = 0;
      risc.BRANCH_TAKEN = 0;

      #500
      for(k=0;k<3;k++)
          $display("R%1d - %2d", k,risc.Reg[k]);
      $display("\nMemory[120] = %4d",risc.Mem[120]);
      $display("\nMemory[121] = %4d",risc.Mem[121]);
  end

initial
  begin
      $dumpfile("test2.vcd");
      $dumpvars(0,test2);
      #600 $finish;
  end

endmodule

2_PROJECT(RISC_processor)/test2.vcd
$date
	Sat Oct 05 23:23:58 2019
$end
$version
	Icarus Verilog
$end
$timescale
	10ps
$end
$scope module test2 $end
$var reg 1 ! clk1 $end
$var reg 1 " clk2 $end
$var integer 32 # k [31:0] $end
$scope module risc $end
$var wire 1 ! clk1 $end
$var wire 1 " clk2 $end
$var reg 1 $ BRANCH_TAKEN $end
$var reg 32 % EX_MEM_ALUout [31:0] $end
$var reg 32 & EX_MEM_B [31:0] $end
$var reg 1 ' EX_MEM_Cond $end
$var reg 32 ( EX_MEM_IR [31:0] $end
$var reg 3 ) EX_MEM_type [2:0] $end
$var reg 1 * HALTED $end
$var reg 32 + ID_EX_A [31:0] $end
$var reg 32 , ID_EX_B [31:0] $end
$var reg 32 - ID_EX_IR [31:0] $end
$var reg 32 . ID_EX_Imm [31:0] $end
$var reg 32 / ID_EX_NPC [31:0] $end
$var reg 3 0 ID_EX_type [2:0] $end
$var reg 32 1 IF_ID_IR [31:0] $end
$var reg 32 2 IF_ID_NPC [31:0] $end
$var reg 32 3 MEM_WB_ALUout [31:0] $end
$var reg 32 4 MEM_WB_IR [31:0] $end
$var reg 32 5 MEM_WB_LMD [31:0] $end
$var reg 3 6 MEM_WB_type [2:0] $end
$var reg 32 7 PC [31:0] $end
$upscope $end
$upscope $end
$enddefinitions $end
#0
$dumpvars
b1 7
bx 6
bx 5
bx 4
bx 3
bx 2
bx 1
bx 0
bx /
bx .
bx -
bx ,
bx +
0*
bx )
bx (
x'
bx &
bx %
0$
b100000 #
0"
0!
$end
#500
1!
#700
b10 7
b10 2
b101000000000010000000001111000 1
#1000
0!
#1500
b0 +
1"
#1700
b1 0
b1111000 .
b101000000000010000000001111000 -
b10 /
b1 ,
#2000
0"
#2500
1!
#2700
b1111000 %
b101000000000010000000001111000 (
b1 )
b11 7
b11 2
b1100111001110111100000000000 1
#3000
0!
#3500
1"
#3700
b1111000 3
b1 6
b101000000000010000000001111000 4
b0 0
b111100000000000 .
b1100111001110111100000000000 -
b11 /
b111 ,
b111 +
#4000
0"
#4500
1!
#4700
b100 7
b100 2
b100000001000100000000000000000 1
b111 %
b1100111001110111100000000000 (
b0 )
#5000
0!
#5500
1"
#5700
b10 0
b0 .
b100000001000100000000000000000 -
b100 /
b10 ,
b1111000 +
b111 3
b0 6
b1100111001110111100000000000 4
#6000
0"
#6500
1!
#6700
b10 &
b1111000 %
b100000001000100000000000000000 (
b10 )
b101 7
b101 2
b1100111001110111100000000000 1
#7000
0!
#7500
1"
#7700
b10 6
b100000001000100000000000000000 4
b0 0
b111100000000000 .
b1100111001110111100000000000 -
b101 /
b111 ,
b111 +
#7900
b101000 5
#8000
0"
#8500
1!
#8700
b110 7
b110 2
b101100010000100000000000001010 1
b111 %
b1100111001110111100000000000 (
b0 )
#9000
0!
#9500
1"
#9700
b1 0
b1010 .
b101100010000100000000000001010 -
b110 /
b101000 ,
b101000 +
b0 6
b1100111001110111100000000000 4
#10000
0"
#10500
1!
#10700
b11110 %
b101100010000100000000000001010 (
b1 )
b111 7
b111 2
b1100111001110111100000000000 1
#11000
0!
#11500
1"
#11700
b11110 3
b1 6
b101100010000100000000000001010 4
b0 0
b111100000000000 .
b1100111001110111100000000000 -
b111 /
b111 ,
b111 +
#12000
0"
#12500
1!
#12700
b1000 7
b1000 2
b100100001000100000000000000001 1
b111 %
b1100111001110111100000000000 (
b0 )
#13000
0!
#13500
1"
#13700
b11 0
b1 .
b100100001000100000000000000001 -
b1000 /
b11110 ,
b1111000 +
b111 3
b0 6
b1100111001110111100000000000 4
#14000
0"
#14500
1!
#14700
b11110 &
b1111001 %
b100100001000100000000000000001 (
b11 )
b1001 7
b1001 2
b11111100000000000000000000000000 1
#15000
0!
#15500
b0 ,
b0 +
1"
#15700
b11 6
b100100001000100000000000000001 4
b101 0
b0 .
b11111100000000000000000000000000 -
b1001 /
#16000
0"
#16500
1!
#16700
b1010 7
b1010 2
bx 1
b11111100000000000000000000000000 (
b101 )
#17000
0!
#17500
1"
#17700
bx .
bx -
b1010 /
bx ,
bx +
b101 6
b11111100000000000000000000000000 4
#18000
0"
#18500
1!
#18700
1*
bx (
b1011 7
b1011 2
