combinational_ckt/half_adder/half_adder.v
module half_adder(
    input x,
    input y,
    output sum,
    output carry
);

assign sum = x^y;
assign carry = x&y;

endmodule

combinational_ckt/full_adder/full_adder.v
/* Module for full adder using two half adders*/

`include "half_adder.v"

module full_adder(
    input A,
    input B,
    input Z,
    output sum,
    output carr
);

wire s1;
wire c1;
wire c2;

half_adder HA1(A,B,s1,c1);
half_adder HA2(s1,Z,sum,c2);

assign carr = c1|c2;

endmodule

combinational_ckt/full_adder/full_adder_tb.v
/* Testbench for the full adder module*/

`timescale 1ns/1ns
`include "full_adder.v"

module full_adder_tb();
    reg x;
    reg y;
    reg z;
    wire s;
    wire c;

full_adder DUT(x,y,z,s,c);

initial
begin
    $monitor("x=%b, y=%b, z=%b, sum=%b, carry=%b",x,y,z,s,c);
    $dumpfile("fa_tb.vcd");
    $dumpvars(0,full_adder_tb);

    x=0; y=0; z=0; #10;
    x=0; y=0; z=1; #10;
    x=0; y=1; z=0; #10;
    x=0; y=1; z=1; #10;
    x=1; y=0; z=0; #10;
    x=1; y=0; z=1; #10;
    x=1; y=1; z=0; #10;
    x=1; y=1; z=1; #10;

    $finish;
end

endmodule

combinational_ckt/full_adder/fa_tb.vcd
$date
	Wed Jun 05 00:42:54 2019
$end
$version
	Icarus Verilog
$end
$timescale
	1ns
$end
$scope module full_adder_tb $end
$var wire 1 ! s $end
$var wire 1 " c $end
$var reg 1 # x $end
$var reg 1 $ y $end
$var reg 1 % z $end
$scope module DUT $end
$var wire 1 # A $end
$var wire 1 $ B $end
$var wire 1 % Z $end
$var wire 1 " carr $end
$var wire 1 ! sum $end
$var wire 1 & s1 $end
$var wire 1 ' c2 $end
$var wire 1 ( c1 $end
$scope module HA1 $end
$var wire 1 ( carry $end
$var wire 1 & sum $end
$var wire 1 # x $end
$var wire 1 $ y $end
$upscope $end
$scope module HA2 $end
$var wire 1 ' carry $end
$var wire 1 ! sum $end
$var wire 1 & x $end
$var wire 1 % y $end
$upscope $end
$upscope $end
$upscope $end
$enddefinitions $end
#0
$dumpvars
0(
0'
0&
0%
0$
0#
0"
0!
$end
#10
1!
1%
#20
1&
0%
1$
#30
1"
0!
1'
1%
#40
0"
1!
0'
0%
0$
1#
#50
1"
0!
1'
1%
#60
0'
0&
1(
0%
1$
#70
1!
1%
