1_Project (Booth Multiplier)/controller.v
// Controller for the Booth's Multiplier

module controller(
    ldA,
    clrA,
    sftA,
    ldQ,
    clrQ,
    sftQ,
    clrff,
    ldM,
    addsub,
    ldcount,
    decount,
    done,
    clk,
    q0,
    qd,
    stop,
    start
);

input clk, q0, qd, stop, start;
output reg ldA,clrA,sftA,ldQ,clrQ,sftQ;
output reg ldM,clrff,addsub,ldcount,decount, done;

reg [2:0] state;

parameter S0=3'b000, S1=3'b001, S2=3'b010, S3=3'b011,
          S4=3'b100, S5=3'b101, S6=3'b110;

always @(posedge clk)
begin
    case(state)
      S0:    if (start) state <= S1;
      S1:    state <= S2;
      S2:    if({q0,qd}==2'b01) state <= S3;
             else if ({q0,qd}==2'b10) state <= S4;
             else state <= S5;
      S3:    state <= S5;
      S4:    state <= S5;
      S5:    if(({q0,qd}==2'b01) && (!stop)) state <= S3;
             else if(({q0,qd}==2'b10) && (!stop)) state <= S4;
             else if(stop) state <= S6;
      S6:    state <= S6;
      default:    state <= S0;
    endcase
end

always @(state)
begin
    case(state)
      S0: begin
          ldA=0; clrA=0; sftA=0; ldQ=0; clrQ=0; sftQ=0;
          ldM=0; clrff=0; done=0;    
      end
      S1: begin
          clrA=1; clrff=1; ldcount=1; ldM=1;
      end
      S2: begin
          clrA=0; clrff=0; ldcount=0; ldM=0; ldQ=1;
      end
      S3: begin
          ldA=1; addsub=1; ldQ=0; sftA=0; sftQ=0; decount=0;
      end
      S4: begin
          ldA=1; addsub=0; ldQ=0; sftA=0; sftQ=0; decount=0;
      end
      S5: begin
          ldA=0; ldQ=0; sftA=1; sftQ=1; decount=1;
      end
      S6: begin
          done=1; decount=0; sftA=0; sftQ=0;
      end
      default: begin
          clrA=0; sftA=0; ldQ=0; sftQ=0;
      end
    endcase
end

endmodule

1_Project (Booth Multiplier)/counter.v
// Down counter for Booth's Multiplier

module counter (
    count,
    clk,
    load,
    dec
);

parameter N = 3;    //Number of bits of the counter
parameter M = 8;    //Number of steps in the Booth's algorithn

input clk, load, dec;
output reg [N:0] count;

always @(posedge clk)
begin
    if (load)
        count <= M;
    else if (dec)
        count <= count - 1;    
end

endmodule

1_Project (Booth Multiplier)/alu.v
// ALU module for Booth's Multiplier
// which performs addition and subtraction of
// partial products

module ALU(
    out,
    in1,
    in2,
    addsub
);

parameter N = 8;

input [N-1:0] in1,in2;
input addsub;

output [N-1:0] out;

always @(*)
begin
    if (addsub)
        out = in1+in2;
    else
        out = in1-in2;    
end

endmodule

1_Project (Booth Multiplier)/d_flop.v
// A 1-bit D-FF for Booth Multiplier

module d_flop(
    q,
    d,
    clk,
    clr
);

input d, clk, clr;
output reg q;

always @(negedge clk)
begin
    if (clr)
        q <= 0;
    else
        q <= d;    
end

endmodule

1_Project (Booth Multiplier)/PIPO_reg.v
// A PIPO register for multiplicand application in
// Booth's Multiplier

module PIPO_reg(
    data_out,
    data_in,
    clk,
    load
);

parameter N = 8;

input [N-1:0] data_in;
input clk, load;

output reg [N-1:0] data_out;

always @(negedge clk)
begin
    if(load)
        data_out <= data_in;
end

endmodule

1_Project (Booth Multiplier)/shiftregister.v
//  n-bit Arithmetic right Shift Register module for Booth Multiplier

module shiftreg(
    data_out,
    data_in,
    serial_in,
    clk,
    load,
    clear,
    shift
);

parameter N = 8;

input [N-1:0] data_in;
input serial_in;
input clk, load, clear, shift;

output reg [N-1:0] data_out;

always @(negedge clk)
begin
    if (clear) data_out <= 0;                       //initializing the register
    else if (load) data_out <= data_in;             //loading the register
    else if(shift)
        data_out <= {serial_in,data_out[N-1:1]};   //arithmetic right shift
end

endmodule

1_Project (Booth Multiplier)/data_path.v
// Data Path module for the Booth's Multiplier

`include "shiftregister.v"
`include "PIPO_reg.v"
`include "d_flop.v"
`include "alu.v"
`include "counter.v"

module data_path(
    stop,
    q0,
    qd,
    clk,
    data_in,
    ldA,
    clrA,
    sftA,
    ldQ,
    clrQ,
    sftQ,
    clrff,
    ldM,
    addsub,
    ldcount,
    decount
);

parameter N = 8;

input [N-1:0] data_in;
input clk, ldA, clrA, sftA;
input ldQ, clrQ, sftQ;
input ldM, clrff, addsub, ldcount,decount;

output stop, q0, qd;

wire [N-1:0] A,M,Z,Q;
wire [3:0] count;

assign stop = ~|count;    //to check when count reaches 4'b0000
assign q0 = Q[0];         //q0 gives the LSB of Q(Multiplier)

shiftreg AR(.data_out(A),.data_in(Z),.serial_in(A[N-1]),.clk(clk),.load(ldA),.clear(clrA),.shift(sftA));
shiftreg QR(.data_out(Q),.data_in(data_in),.serial_in(A[0]),.clk(clk),.load(ldQ),.clear(clrQ),.shift(sftQ));
PIPO_reg MR(.data_out(M),.data_in(data_in),.clk(clk),.load(ldM));
d_flop dff(.q(qd),.d(Q[0]),.clk(clk),.clr(clrff));
ALU DUT(.out(Z),.in1(A),.in2(M),.addsub(addsub));
counter CR(.count(count),.clk(clk),.load(ldcount),.dec(decount));

endmodule

1_Project (Booth Multiplier)/test.v
//testbench for Booth's Multiplier

`timescale 1ns/10ps
`include "data_path.v"
`include "controller.v"

module test();
reg [7:0] data_in;
reg start,clk;
wire done;

wire [15:0] result;

data_path dut1(stop,q0,qd,clk,data_in,ldA,clrA,sftA,ldQ,clrQ,sftQ,clrff,ldM,addsub,ldcount,decount);
controller dut2(ldA,clrA,sftA,ldQ,clrQ,sftQ,clrff,ldM,addsub,ldcount,decount,done,clk,q0,qd,stop,start);

assign result = {dut1.A,dut1.Q};

initial
begin
    clk=1'b0;
    start= 0;
    #200 $finish;
end

//Generating CLK signal with time period 10 units
always #5 clk= ~clk;

initial
begin
    #2 start = 1;
    #15 data_in = 8'b00000110;
    #10 data_in = 8'b00000100;
end

initial
begin
    $dumpfile("plot.vcd");
    $dumpvars(0,test);

    $monitor($time," Result : %b", result);
end

endmodule

1_Project (Booth Multiplier)/plot.vcd
$date
	Thu Oct 03 18:11:28 2019
$end
$version
	Icarus Verilog
$end
$timescale
	10ps
$end
$scope module test $end
$var wire 1 ! stop $end
$var wire 1 " sftQ $end
$var wire 1 # sftA $end
$var wire 16 $ result [15:0] $end
$var wire 1 % qd $end
$var wire 1 & q0 $end
$var wire 1 ' ldcount $end
$var wire 1 ( ldQ $end
$var wire 1 ) ldM $end
$var wire 1 * ldA $end
$var wire 1 + done $end
$var wire 1 , decount $end
$var wire 1 - clrff $end
$var wire 1 . clrQ $end
$var wire 1 / clrA $end
$var wire 1 0 addsub $end
$var reg 1 1 clk $end
$var reg 8 2 data_in [7:0] $end
$var reg 1 3 start $end
$scope module dut1 $end
$var wire 1 1 clk $end
$var wire 8 4 data_in [7:0] $end
$var wire 1 ! stop $end
$var wire 1 " sftQ $end
$var wire 1 # sftA $end
$var wire 1 % qd $end
$var wire 1 & q0 $end
$var wire 1 ' ldcount $end
$var wire 1 ( ldQ $end
$var wire 1 ) ldM $end
$var wire 1 * ldA $end
$var wire 1 , decount $end
$var wire 4 5 count [3:0] $end
$var wire 1 - clrff $end
$var wire 1 . clrQ $end
$var wire 1 / clrA $end
$var wire 1 0 addsub $end
$var wire 8 6 Z [7:0] $end
$var wire 8 7 Q [7:0] $end
$var wire 8 8 M [7:0] $end
$var wire 8 9 A [7:0] $end
$scope module AR $end
$var wire 1 1 clk $end
$var wire 1 : serial_in $end
$var wire 1 # shift $end
$var wire 1 * load $end
$var wire 8 ; data_in [7:0] $end
$var wire 1 / clear $end
$var reg 8 < data_out [7:0] $end
$upscope $end
$scope module CR $end
$var wire 1 1 clk $end
$var wire 1 ' load $end
$var wire 1 , dec $end
$var reg 4 = count [3:0] $end
$upscope $end
$scope module DUT $end
$var wire 8 > in1 [7:0] $end
$var wire 8 ? in2 [7:0] $end
$var wire 1 0 addsub $end
$var reg 8 @ out [7:0] $end
$upscope $end
$scope module MR $end
$var wire 1 1 clk $end
$var wire 8 A data_in [7:0] $end
$var wire 1 ) load $end
$var reg 8 B data_out [7:0] $end
$upscope $end
$scope module QR $end
$var wire 1 1 clk $end
$var wire 8 C data_in [7:0] $end
$var wire 1 D serial_in $end
$var wire 1 " shift $end
$var wire 1 ( load $end
$var wire 1 . clear $end
$var reg 8 E data_out [7:0] $end
$upscope $end
$scope module dff $end
$var wire 1 1 clk $end
$var wire 1 F d $end
$var wire 1 - clr $end
$var reg 1 % q $end
$upscope $end
$upscope $end
$scope module dut2 $end
$var wire 1 1 clk $end
$var wire 1 & q0 $end
$var wire 1 % qd $end
$var wire 1 3 start $end
$var wire 1 ! stop $end
$var reg 1 0 addsub $end
$var reg 1 / clrA $end
$var reg 1 . clrQ $end
$var reg 1 - clrff $end
$var reg 1 , decount $end
$var reg 1 + done $end
$var reg 1 * ldA $end
$var reg 1 ) ldM $end
$var reg 1 ( ldQ $end
$var reg 1 ' ldcount $end
$var reg 1 # sftA $end
$var reg 1 " sftQ $end
$var reg 3 G state [2:0] $end
$upscope $end
$upscope $end
$enddefinitions $end
#0
$dumpvars
bx G
xF
bx E
xD
bx C
bx B
bx A
bx @
bx ?
bx >
bx =
bx <
bx ;
x:
bx 9
bx 8
bx 7
bx 6
bx 5
bx 4
03
bx 2
01
x0
x/
x.
x-
x,
x+
x*
x)
x(
x'
x&
x%
bx $
x#
x"
x!
$end
#200
13
#500
0+
0-
0)
0"
0.
0(
0#
0/
0*
b0 G
11
#1000
01
#1500
1)
1'
1-
1/
b1 G
11
#1700
b110 2
b110 4
b110 A
b110 C
#2000
0D
0:
b0xxxxxxxx $
b0 9
b0 <
b0 >
b110 8
b110 ?
b110 B
0%
0!
b1000 5
b1000 =
01
#2500
1(
0)
0'
0-
0/
b10 G
11
#2700
b100 2
b100 4
b100 A
b100 C
#3000
0F
0&
x%
b100 $
b100 7
b100 E
01
#3500
1,
1"
1#
0(
b101 G
11
#4000
b10 $
b10 7
b10 E
0%
b111 5
b111 =
01
#4500
11
#5000
1F
1&
b110 5
b110 =
b1 $
b1 7
b1 E
01
#5500
b11111010 6
b11111010 ;
b11111010 @
0,
0"
0#
00
1*
b100 G
11
#6000
b11110100 6
b11110100 ;
b11110100 @
1:
b1111101000000001 $
b11111010 9
b11111010 <
b11111010 >
1%
01
#6500
1,
1"
1#
0*
b101 G
11
#7000
0F
0&
b11110111 6
b11110111 ;
b11110111 @
1D
b101 5
b101 =
b0 7
b0 E
b1111110100000000 $
b11111101 9
b11111101 <
b11111101 >
01
#7500
b11 6
b11 ;
b11 @
0,
0"
0#
10
1*
b11 G
11
#8000
b1001 6
b1001 ;
b1001 @
0:
b1100000000 $
b11 9
b11 <
b11 >
0%
01
#8500
1,
1"
1#
0*
b101 G
11
#9000
b111 6
b111 ;
b111 @
b100 5
b100 =
b10000000 7
b10000000 E
b110000000 $
b1 9
b1 <
b1 >
01
#9500
11
#10000
b110 6
b110 ;
b110 @
0D
b0 9
b0 <
b0 >
b11000000 $
b11000000 7
b11000000 E
b11 5
b11 =
01
#10500
11
#11000
b10 5
b10 =
b1100000 $
b1100000 7
b1100000 E
01
#11500
11
#12000
b110000 $
b110000 7
b110000 E
b1 5
b1 =
01
#12500
11
#13000
1!
b0 5
b0 =
b11000 $
b11000 7
b11000 E
01
#13500
0"
0#
0,
1+
b110 G
11
