Pipelining/example_1/pipe1.v
//Pipelining example - 1
//A combinational logic system with :
//Four N-bit unsigned numbers A,B,C and D ans inputs
//An N-bit number F as output
//The logic is given in three stages:
// S1 : x1 = A+B; x2 = C-D;
// S2 : x3 = x1+x2;
// S3 : F = x3*D;

module pipe1(
    F,A,B,C,D,clk
);

parameter N = 8;

output [N-1:0] F;
input [N-1:0] A,B,C,D;
input clk;

reg [N-1:0] L12_x1, L12_x2, L12_D, L23_x3, L23_D, L34_F;

assign F = L34_F;    // assigning the output reg to wire output F

//stage 1
always @(posedge clk)
begin
    L12_x1 <= #4 A + B;
    L12_x2 <= #4 C - D;
    L12_D  <= D;
end

//stage 2
always @(posedge clk)
begin
    L23_x3 <= #4 L12_x1 + L12_x2;
    L23_D  <= L12_D;
end

//stage 3
always @(posedge clk)
begin
    L34_F <= #6 L23_x3 * L23_D;
end

endmodule

Pipelining/example_1/pipe1_tb.v
//Testbench for the pipe1 module
`include "pipe1.v"

module pipe1_tb();
parameter N = 8;
wire [N-1:0] F;
reg [N-1:0] A,B,C,D;
reg clk;

pipe1 DUT(F,A,B,C,D,clk);

// Clock signal initialization
initial
begin
    clk = 1'b0;
end

// Clock signal with time period 10 units
always
begin
    #10 clk = ~clk;
end

initial
begin
    $dumpfile("plot.vcd");
    $dumpvars(0,pipe1_tb);
    $monitor($time, " A=%h B=%h C=%h D=%h F=%h", A,B,C,D,F);

    #250 $finish;
end

//The stream of inputs
initial
begin
    #5  A=1; B=1; C=2; D=1;
    #20 A=2; B=3; C=4; D=2;
    #20 A=3; B=5; C=6; D=3;    
    #20 A=4; B=7; C=8; D=4;
    #20 A=5; B=9; C=10; D=5;
    #20 A=6; B=11; C=12; D=6;
    #20 A=7; B=13; C=14; D=7;
    #20 A=8; B=15; C=16; D=8;
    #20 A=9; B=17; C=18; D=9;
    #20 A=10; B=19; C=20; D=10;
    #20 A=11; B=21; C=22; D=11;
end

endmodule

Pipelining/example_1/plot.vcd
$date
	Mon Sep 30 00:05:10 2019
$end
$version
	Icarus Verilog
$end
$timescale
	1s
$end
$scope module pipe1_tb $end
$var wire 8 ! F [7:0] $end
$var reg 8 " A [7:0] $end
$var reg 8 # B [7:0] $end
$var reg 8 $ C [7:0] $end
$var reg 8 % D [7:0] $end
$var reg 1 & clk $end
$scope module DUT $end
$var wire 8 ' A [7:0] $end
$var wire 8 ( B [7:0] $end
$var wire 8 ) C [7:0] $end
$var wire 8 * D [7:0] $end
$var wire 8 + F [7:0] $end
$var wire 1 & clk $end
$var reg 8 , L12_D [7:0] $end
$var reg 8 - L12_x1 [7:0] $end
$var reg 8 . L12_x2 [7:0] $end
$var reg 8 / L23_D [7:0] $end
$var reg 8 0 L23_x3 [7:0] $end
$var reg 8 1 L34_F [7:0] $end
$upscope $end
$upscope $end
$enddefinitions $end
#0
$dumpvars
bx 1
bx 0
bx /
bx .
bx -
bx ,
bx +
bx *
bx )
bx (
bx '
0&
bx %
bx $
bx #
bx "
bx !
$end
#5
b1 %
b1 *
b10 $
b10 )
b1 #
b1 (
b1 "
b1 '
#10
b1 ,
1&
#14
b1 .
b10 -
#20
0&
#25
b10 %
b10 *
b100 $
b100 )
b11 #
b11 (
b10 "
b10 '
#30
b1 /
b10 ,
1&
#34
b11 0
b10 .
b101 -
#40
0&
#45
b11 %
b11 *
b110 $
b110 )
b101 #
b101 (
b11 "
b11 '
#50
b11 ,
b10 /
1&
#54
b11 .
b1000 -
b111 0
#56
b11 !
b11 +
b11 1
#60
0&
#65
b100 %
b100 *
b1000 $
b1000 )
b111 #
b111 (
b100 "
b100 '
#70
b11 /
b100 ,
1&
#74
b1011 0
b100 .
b1011 -
#76
b1110 !
b1110 +
b1110 1
#80
0&
#85
b101 %
b101 *
b1010 $
b1010 )
b1001 #
b1001 (
b101 "
b101 '
#90
b101 ,
b100 /
1&
#94
b101 .
b1110 -
b1111 0
#96
b100001 !
b100001 +
b100001 1
#100
0&
#105
b110 %
b110 *
b1100 $
b1100 )
b1011 #
b1011 (
b110 "
b110 '
#110
b101 /
b110 ,
1&
#114
b10011 0
b110 .
b10001 -
#116
b111100 !
b111100 +
b111100 1
#120
0&
#125
b111 %
b111 *
b1110 $
b1110 )
b1101 #
b1101 (
b111 "
b111 '
#130
b111 ,
b110 /
1&
#134
b111 .
b10100 -
b10111 0
#136
b1011111 !
b1011111 +
b1011111 1
#140
0&
#145
b1000 %
b1000 *
b10000 $
b10000 )
b1111 #
b1111 (
b1000 "
b1000 '
#150
b111 /
b1000 ,
1&
#154
b11011 0
b1000 .
b10111 -
#156
b10001010 !
b10001010 +
b10001010 1
#160
0&
#165
b1001 %
b1001 *
b10010 $
b10010 )
b10001 #
b10001 (
b1001 "
b1001 '
#170
b1001 ,
b1000 /
1&
#174
b1001 .
b11010 -
b11111 0
#176
b10111101 !
b10111101 +
b10111101 1
#180
0&
#185
b1010 %
b1010 *
b10100 $
b10100 )
b10011 #
b10011 (
b1010 "
b1010 '
#190
b1001 /
b1010 ,
1&
#194
b100011 0
b1010 .
b11101 -
#196
b11111000 !
b11111000 +
b11111000 1
#200
0&
#205
b1011 %
b1011 *
b10110 $
b10110 )
b10101 #
b10101 (
b1011 "
b1011 '
#210
b1011 ,
b1010 /
1&
#214
b1011 .
b100000 -
b100111 0
#216
b111011 !
b111011 +
b111011 1
#220
0&
#230
b1011 /
1&
#234
b101011 0
#236
b10000110 !
b10000110 +
b10000110 1
