combinational_ckt/decoder/dec4to16.v
/* Verilog module for a 4 to 16 bit decoder with enable inout*/

module decoder(
    output [15:0] out,
    input [3:0] in,
    input en
);

reg [15:0] out;

always @(en,in)
    if(en)
        out = 16'h0000;
    else    
    case(in)
    4'b0000: out = 16'h0001;
    4'b0001: out = 16'h0002;
    4'b0010: out = 16'h0004;
    4'b0011: out = 16'h0008;
    4'b0100: out = 16'h0010;
    4'b0101: out = 16'h0020;
    4'b0110: out = 16'h0040;
    4'b0111: out = 16'h0080;
    4'b1000: out = 16'h0100;
    4'b1001: out = 16'h0200;
    4'b1010: out = 16'h0400;
    4'b1011: out = 16'h0800;
    4'b1100: out = 16'h1000;
    4'b1101: out = 16'h2000;
    4'b1110: out = 16'h4000;
    4'b1111: out = 16'h8000;
    default: out = 16'h0;
    endcase

endmodule

combinational_ckt/decoder/dec4to16_tb.v
/* Testbench for the decoder module*/

`timescale 1ns/1ns
`include "dec4to16.v"

module decoder_tb();
wire [15:0] out;
reg [3:0] in;
reg en;

integer k;
decoder dut(.out(out), .in(in), .en(en));

initial begin
    $dumpfile("plot.vcd");
    $dumpvars(0,decoder_tb);
    en = 1; #10;
    en = 0;
    for(k=0;k<16;++k) begin
        in = k; #10;
    end

    $finish;
end

endmodule

combinational_ckt/decoder/plot.vcd
$date
	Wed Jul 31 11:57:42 2019
$end
$version
	Icarus Verilog
$end
$timescale
	1ns
$end
$scope module decoder_tb $end
$var wire 16 ! out [15:0] $end
$var reg 1 " en $end
$var reg 4 # in [3:0] $end
$var integer 32 $ k [31:0] $end
$scope module dut $end
$var wire 1 " en $end
$var wire 4 % in [3:0] $end
$var reg 16 & out [15:0] $end
$upscope $end
$upscope $end
$enddefinitions $end
#0
$dumpvars
b0 &
bx %
bx $
bx #
1"
b0 !
$end
#10
b1 !
b1 &
b0 #
b0 %
b0 $
0"
#20
b10 !
b10 &
b1 #
b1 %
b1 $
#30
b100 !
b100 &
b10 #
b10 %
b10 $
#40
b1000 !
b1000 &
b11 #
b11 %
b11 $
#50
b10000 !
b10000 &
b100 #
b100 %
b100 $
#60
b100000 !
b100000 &
b101 #
b101 %
b101 $
#70
b1000000 !
b1000000 &
b110 #
b110 %
b110 $
#80
b10000000 !
b10000000 &
b111 #
b111 %
b111 $
#90
b100000000 !
b100000000 &
b1000 #
b1000 %
b1000 $
#100
b1000000000 !
b1000000000 &
b1001 #
b1001 %
b1001 $
#110
b10000000000 !
b10000000000 &
b1010 #
b1010 %
b1010 $
#120
b100000000000 !
b100000000000 &
b1011 #
b1011 %
b1011 $
#130
b1000000000000 !
b1000000000000 &
b1100 #
b1100 %
b1100 $
#140
b10000000000000 !
b10000000000000 &
b1101 #
b1101 %
b1101 $
#150
b100000000000000 !
b100000000000000 &
b1110 #
b1110 %
b1110 $
#160
b1000000000000000 !
b1000000000000000 &
b1111 #
b1111 %
b1111 $
#170
b10000 $
